astronaut/__init__.py
astronaut/app.py
astronaut/settings.py
astronaut/domain/__init__.py
astronaut/domain/space.py
astronaut/repository/__init__.py
astronaut/repository/memrepo.py
astronaut/rest/__init__.py
astronaut/rest/space.py
astronaut/serializers/__init__.py
astronaut/serializers/space_serializer.py
astronaut/shared/__init__.py
astronaut/shared/domain_model.py
astronaut/shared/request_object.py
astronaut/shared/response_object.py
astronaut/shared/use_case.py
astronaut/use_cases/__init__.py
astronaut/use_cases/request_objects.py
astronaut/use_cases/space_use_cases.py
astronaut-0.1.3.dist-info/METADATA
astronaut-0.1.3.dist-info/RECORD
astronaut-0.1.3.dist-info/WHEEL
astronaut-0.1.3.dist-info/top_level.txt
tests/domain/__init__.py
tests/domain/test_space.py
tests/repository/__init__.py
tests/repository/test_memrepo.py
tests/serializers/__init__.py
tests/serializers/test_space_serializer.py
tests/shared/__init__.py
tests/shared/test_request_object.py
tests/shared/test_response_object.py
tests/shared/test_use_case.py
tests/use_cases/__init__.py
tests/use_cases/test_space_list_request_objects.py
tests/use_cases/test_space_list_use_case.py
