Metadata-Version: 2.1
Name: astronaut
Version: 0.1.3
Summary: A framework for AI to explore spaces
Home-page: https://github.com/RobotStudio/astronaut
Author: Bobby Larson
Author-email: bobby@robot.studio
License: GNU General Public License v3
Keywords: astronaut
Platform: UNKNOWN
Classifier: Development Status :: 2 - Pre-Alpha
Classifier: Intended Audience :: Developers
Classifier: License :: OSI Approved :: GNU General Public License v3 (GPLv3)
Classifier: Natural Language :: English
Classifier: Programming Language :: Python :: 2
Classifier: Programming Language :: Python :: 2.6
Classifier: Programming Language :: Python :: 2.7
Classifier: Programming Language :: Python :: 3
Classifier: Programming Language :: Python :: 3.3
Classifier: Programming Language :: Python :: 3.4
Classifier: Programming Language :: Python :: 3.5
Classifier: Programming Language :: Python :: 3.6
Requires-Dist: apiwrapper
